gbb_excel_mcp/__init__.py
gbb_excel_mcp/gbb.py
gbb_excel_mcp/pro_collect_dify.py
gbb_excel_mcp/pro_suit_dify.py
gbb_excel_mcp/server.py
gbb_excel_mcp-0.1.7.dist-info/METADATA
gbb_excel_mcp-0.1.7.dist-info/WHEEL
gbb_excel_mcp-0.1.7.dist-info/entry_points.txt
gbb_excel_mcp-0.1.7.dist-info/RECORD
