Metadata-Version: 2.4
Name: gbb-excel-mcp
Version: 0.1.7
Summary: excel文件中内容匹配工邦邦商品sku
Author-email: "meng4.wang" <meng4.wang@gongbangbang.com>
Keywords: gbb,mcp,server
Requires-Python: >=3.10
Requires-Dist: fastapi>=0.95.0
Requires-Dist: mcp>=1.9.0
Requires-Dist: python-multipart>=0.0.6
Requires-Dist: requests>=2.28.0
Requires-Dist: uvicorn>=0.21.0
